aioposter/__init__.py
aioposter/client.py
aioposter/server.py
aioposter-0.0.5.dist-info/METADATA
aioposter-0.0.5.dist-info/WHEEL
aioposter-0.0.5.dist-info/RECORD
