Metadata-Version: 2.1
Name: aioposter
Version: 0.0.5
Summary: ok
Author: aldf
Author-email: dafiosl@gmail.com
Requires-Python: >=3.8,<4.0
Classifier: Programming Language :: Python :: 3
Classifier: Programming Language :: Python :: 3.8
Classifier: Programming Language :: Python :: 3.9
Classifier: Programming Language :: Python :: 3.10
Classifier: Programming Language :: Python :: 3.11
Requires-Dist: aio-pika (>=9.1.4,<10.0.0)
Requires-Dist: aiohttp (>=3.7,<4.0)
Requires-Dist: python-dotenv (>=1.0.0,<2.0.0)
Requires-Dist: rich (>=10.0,<11.0)
Requires-Dist: simauth (>=0.0.9,<0.0.10)
Requires-Dist: urllib3 (>=1.26.18,<2.0.0)
